uri/__init__.py
uri/bucket.py
uri/compat.py
uri/qso.py
uri/release.py
uri/scheme.py
uri/uri.py
uri/__pycache__/__init__.cpython-37.opt-1.pyc
uri/__pycache__/bucket.cpython-37.opt-1.pyc
uri/__pycache__/compat.cpython-37.opt-1.pyc
uri/__pycache__/qso.cpython-37.opt-1.pyc
uri/__pycache__/release.cpython-37.opt-1.pyc
uri/__pycache__/scheme.cpython-37.opt-1.pyc
uri/__pycache__/uri.cpython-37.opt-1.pyc
uri/part/__init__.py
uri/part/auth.py
uri/part/authority.py
uri/part/base.py
uri/part/fragment.py
uri/part/heir.py
uri/part/host.py
uri/part/password.py
uri/part/path.py
uri/part/port.py
uri/part/query.py
uri/part/scheme.py
uri/part/uri.py
uri/part/user.py
uri/part/__pycache__/__init__.cpython-37.opt-1.pyc
uri/part/__pycache__/auth.cpython-37.opt-1.pyc
uri/part/__pycache__/authority.cpython-37.opt-1.pyc
uri/part/__pycache__/base.cpython-37.opt-1.pyc
uri/part/__pycache__/fragment.cpython-37.opt-1.pyc
uri/part/__pycache__/heir.cpython-37.opt-1.pyc
uri/part/__pycache__/host.cpython-37.opt-1.pyc
uri/part/__pycache__/password.cpython-37.opt-1.pyc
uri/part/__pycache__/path.cpython-37.opt-1.pyc
uri/part/__pycache__/port.cpython-37.opt-1.pyc
uri/part/__pycache__/query.cpython-37.opt-1.pyc
uri/part/__pycache__/scheme.cpython-37.opt-1.pyc
uri/part/__pycache__/uri.cpython-37.opt-1.pyc
uri/part/__pycache__/user.cpython-37.opt-1.pyc
uri-2.0.1.dist-info/METADATA
uri-2.0.1.dist-info/RECORD
uri-2.0.1.dist-info/WHEEL
uri-2.0.1.dist-info/entry_points.txt
uri-2.0.1.dist-info/top_level.txt
